Workbook

Sheet 01_Cover
A1: SALES PERFORMANCE & REVENUE ANALYTICS DASHBOARD
A4: Portfolio Project | Business Analyst / Sales Operations Analyst
A6: Industry: Retail / FMCG / E-commerce
A7: Tool: Microsoft Excel
A8: Dataset: 6,000 realistic sales transactions | Jan-2025 to Aug-2026
A10: Objective: Monitor revenue, profitability, targets, regional performance, products and salespeople.
A12: Workbook flow: Raw Data → Cleaning → Calculations → Targets → Analysis → Dashboard → Insights

Sheet 02_Sales_Data
A1: Order ID | B1: Order Date | C1: Region | D1: State | E1: Salesperson | F1: Customer | G1: Category | H1: Product | I1: Qty | J1: Unit Price | K1: Discount | L1: Sales | M1: Cost | N1: Profit | O1: Profit Margin | P1: Month | Q1: Year
A2: SO00001 | B2: 45772 | C2: North | D2: Haryana | E2: Sneha | F2: Global Mart | G2: Electronics | H2: Printer | I2: 24 | J2: 12500 | K2: 0 | L2: 300000 | M2: 236650.49 | N2: 63349.51 | O2: 0.21116503 | P2: Apr-2025 | Q2: 2025
A3: SO00002 | B3: 46216 | C3: North | D3: Uttar Pradesh | E3: Amit | F3: ABC Retail | G3: Electronics | H3: Monitor | I3: 7 | J3: 18000 | K3: 0.02 | L3: 123480 | M3: 98817.06 | N3: 24662.94 | O3: 0.19973226 | P3: Jul-2026 | Q3: 2026
A4: SO00003 | B4: 45685 | C4: South | D4: Andhra Pradesh | E4: Sneha | F4: City Bazaar | G4: Accessories | H4: Mouse | I4: 9 | J4: 950 | K4: 0 | L4: 8550 | M4: 6437.64 | N4: 2112.36 | O4: 0.24705965 | P4: Jan-2025 | Q4: 2025
A5: SO00004 | B5: 45821 | C5: West | D5: Rajasthan | E5: Vikram | F5: PQR Ltd | G5: Electronics | H5: Keyboard | I5: 25 | J5: 1800 | K5: 0.03 | L5: 43650 | M5: 31869.32 | N5: 11780.68 | O5: 0.26988958 | P5: Jun-2025 | Q5: 2025
A6: SO00005 | B6: 46047 | C6: North | D6: Haryana | E6: Neha | F6: Metro Traders | G6: Office Supplies | H6: Pen Set | I6: 2 | J6: 280 | K6: 0.1 | L6: 504 | M6: 311.46 | N6: 192.54 | O6: 0.38202381 | P6: Jan-2026 | Q6: 2026
A7: SO00006 | B7: 45785 | C7: West | D7: Maharashtra | E7: Vikram | F7: Prime Retail | G7: Accessories | H7: Mouse | I7: 7 | J7: 950 | K7: 0.1 | L7: 5985 | M7: 4300.09 | N7: 1684.91 | O7: 0.28152214 | P7: May-2025 | Q7: 2025
A8: SO00007 | B8: 45891 | C8: East | D8: Odisha | E8: Sneha | F8: XYZ Store | G8: Furniture | H8: Storage Cabinet | I8: 9 | J8: 9000 | K8: 0.05 | L8: 76950 | M8: 56695.55 | N8: 20254.45 | O8: 0.26321572 | P8: Aug-2025 | Q8: 2025
A9: SO00008 | B9: 46031 | C9: South | D9: Tamil Nadu | E9: Neha | F9: Global Mart | G9: Office Supplies | H9: Notebook Pack | I9: 9 | J9: 450 | K9: 0.1 | L9: 3645 | M9: 2448.83 | N9: 1196.17 | O9: 0.32816735 | P9: Jan-2026 | Q9: 2026
A10: SO00009 | B10: 45731 | C10: South | D10: Karnataka | E10: Rahul | F10: City Bazaar | G10: Furniture | H10: Storage Cabinet | I10: 9 | J10: 9000 | K10: 0.1 | L10: 72900 | M10: 53902.85 | N10: 18997.15 | O10: 0.26059191 | P10: Mar-2025 | Q10: 2025
A11: SO00010 | B11: 45882 | C11: East | D11: Odisha | E11: Sneha | F11: ABC Retail | G11: Office Supplies | H11: Pen Set | I11: 11 | J11: 280 | K11: 0.05 | L11: 2926 | M11: 1780.14 | N11: 1145.86 | O11: 0.39161312 | P11: Aug-2025 | Q11: 2025
A12: SO00011 | B12: 45874 | C12: East | D12: West Bengal | E12: Kavya | F12: Star Distributors | G12: Networking | H12: Network Switch | I12: 21 | J12: 8500 | K12: 0.05 | L12: 169575 | M12: 130936.25 | N12: 38638.75 | O12: 0.22785641 | P12: Aug-2025 | Q12: 2025
A13: SO00012 | B13: 45800 | C13: South | D13: Tamil Nadu | E13: Arjun | F13: Star Distributors | G13: Furniture | H13: Work Desk | I13: 8 | J13: 12000 | K13: 0.02 | L13: 94080 | M13: 67782.41 | N13: 26297.59 | O13: 0.2795237 | P13: May-2025 | Q13: 2025
... A6001: SO06000 | B6001: 45831 | C6001: South | D6001: Tamil Nadu | E6001: Priya | F6001: PQR Ltd | G6001: Electronics | H6001: Laptop | I6001: 20 | J6001: 55000 | K6001: 0.03 | L6001: 1067000 | M6001: 867761.21 | N6001: 199238.79 | O6001: 0.18672801 | P6001: Jun-2025 | Q6001: 2025

Sheet 03_Data_Cleaning
A1: Order ID | B1: Order Date | C1: Region | D1: State | E1: Salesperson | F1: Customer | G1: Category | H1: Product | I1: Qty | J1: Unit Price | K1: Discount | L1: Sales | M1: Cost | N1: Profit | O1: Profit Margin | P1: Month | Q1: Year
A2: ='02_Sales_Data'!A2 | B2: ='02_Sales_Data'!B2 | C2: ='02_Sales_Data'!C2 | D2: ='02_Sales_Data'!D2 | E2: ='02_Sales_Data'!E2 | F2: ='02_Sales_Data'!F2 | G2: ='02_Sales_Data'!G2 | H2: ='02_Sales_Data'!H2 | ... Q2: ='02_Sales_Data'!Q2
A3: ='02_Sales_Data'!A3 | B3: ='02_Sales_Data'!B3 | C3: ='02_Sales_Data'!C3 | D3: ='02_Sales_Data'!D3 | E3: ='02_Sales_Data'!E3 | F3: ='02_Sales_Data'!F3 | G3: ='02_Sales_Data'!G3 | H3: ='02_Sales_Data'!H3 | ... Q3: ='02_Sales_Data'!Q3
A4: ='02_Sales_Data'!A4 | B4: ='02_Sales_Data'!B4 | C4: ='02_Sales_Data'!C4 | D4: ='02_Sales_Data'!D4 | E4: ='02_Sales_Data'!E4 | F4: ='02_Sales_Data'!F4 | G4: ='02_Sales_Data'!G4 | H4: ='02_Sales_Data'!H4 | ... Q4: ='02_Sales_Data'!Q4
A5: ='02_Sales_Data'!A5 | B5: ='02_Sales_Data'!B5 | C5: ='02_Sales_Data'!C5 | D5: ='02_Sales_Data'!D5 | E5: ='02_Sales_Data'!E5 | F5: ='02_Sales_Data'!F5 | G5: ='02_Sales_Data'!G5 | H5: ='02_Sales_Data'!H5 | ... Q5: ='02_Sales_Data'!Q5
A6: ='02_Sales_Data'!A6 | B6: ='02_Sales_Data'!B6 | C6: ='02_Sales_Data'!C6 | D6: ='02_Sales_Data'!D6 | E6: ='02_Sales_Data'!E6 | F6: ='02_Sales_Data'!F6 | G6: ='02_Sales_Data'!G6 | H6: ='02_Sales_Data'!H6 | ... Q6: ='02_Sales_Data'!Q6
A7: ='02_Sales_Data'!A7 | B7: ='02_Sales_Data'!B7 | C7: ='02_Sales_Data'!C7 | D7: ='02_Sales_Data'!D7 | E7: ='02_Sales_Data'!E7 | F7: ='02_Sales_Data'!F7 | G7: ='02_Sales_Data'!G7 | H7: ='02_Sales_Data'!H7 | ... Q7: ='02_Sales_Data'!Q7
A8: ='02_Sales_Data'!A8 | B8: ='02_Sales_Data'!B8 | C8: ='02_Sales_Data'!C8 | D8: ='02_Sales_Data'!D8 | E8: ='02_Sales_Data'!E8 | F8: ='02_Sales_Data'!F8 | G8: ='02_Sales_Data'!G8 | H8: ='02_Sales_Data'!H8 | ... Q8: ='02_Sales_Data'!Q8
A9: ='02_Sales_Data'!A9 | B9: ='02_Sales_Data'!B9 | C9: ='02_Sales_Data'!C9 | D9: ='02_Sales_Data'!D9 | E9: ='02_Sales_Data'!E9 | F9: ='02_Sales_Data'!F9 | G9: ='02_Sales_Data'!G9 | H9: ='02_Sales_Data'!H9 | ... Q9: ='02_Sales_Data'!Q9
A10: ='02_Sales_Data'!A10 | B10: ='02_Sales_Data'!B10 | C10: ='02_Sales_Data'!C10 | D10: ='02_Sales_Data'!D10 | E10: ='02_Sales_Data'!E10 | F10: ='02_Sales_Data'!F10 | G10: ='02_Sales_Data'!G10 | H10: ='02_Sales_Data'!H10 | ... Q10: ='02_Sales_Data'!Q10
A11: ='02_Sales_Data'!A11 | B11: ='02_Sales_Data'!B11 | C11: ='02_Sales_Data'!C11 | D11: ='02_Sales_Data'!D11 | E11: ='02_Sales_Data'!E11 | F11: ='02_Sales_Data'!F11 | G11: ='02_Sales_Data'!G11 | H11: ='02_Sales_Data'!H11 | ... Q11: ='02_Sales_Data'!Q11
A12: ='02_Sales_Data'!A12 | B12: ='02_Sales_Data'!B12 | C12: ='02_Sales_Data'!C12 | D12: ='02_Sales_Data'!D12 | E12: ='02_Sales_Data'!E12 | F12: ='02_Sales_Data'!F12 | G12: ='02_Sales_Data'!G12 | H12: ='02_Sales_Data'!H12 | ... Q12: ='02_Sales_Data'!Q12
A13: ='02_Sales_Data'!A13 | B13: ='02_Sales_Data'!B13 | C13: ='02_Sales_Data'!C13 | D13: ='02_Sales_Data'!D13 | E13: ='02_Sales_Data'!E13 | F13: ='02_Sales_Data'!F13 | G13: ='02_Sales_Data'!G13 | H13: ='02_Sales_Data'!H13 | ... Q13: ='02_Sales_Data'!Q13
... A6001: ='02_Sales_Data'!A6001 | B6001: ='02_Sales_Data'!B6001 | C6001: ='02_Sales_Data'!C6001 | D6001: ='02_Sales_Data'!D6001 | E6001: ='02_Sales_Data'!E6001 | F6001: ='02_Sales_Data'!F6001 | G6001: ='02_Sales_Data'!G6001 | H6001: ='02_Sales_Data'!H6001 | ... Q6001: ='02_Sales_Data'!Q6001

Sheet 04_Calculations
A1: Metric | B1: Value
A2: Total Sales | B2: =SUM('02_Sales_Data'!L:L)
A3: Total Profit | B3: =SUM('02_Sales_Data'!N:N)
A4: Profit Margin | B4: =B3/B2
A5: Total Orders | B5: =COUNTA('02_Sales_Data'!A:A)-1
A6: Units Sold | B6: =SUM('02_Sales_Data'!I:I)
A7: Average Order Value | B7: =B2/B5
A8: Sales Target | B8: =SUM('05_Targets'!E:E)
A9: Target Achievement | B9: =B2/B8

Sheet 05_Targets
A1: Month Start | B1: Month | C1: Year | D1: Region | E1: Sales Target
A2: 45658 | B2: Jan-2025 | C2: 2025 | D2: North | E2: 1052380
A3: 45658 | B3: Jan-2025 | C3: 2025 | D3: South | E3: 765005
A4: 45658 | B4: Jan-2025 | C4: 2025 | D4: East | E4: 1000568
A5: 45658 | B5: Jan-2025 | C5: 2025 | D5: West | E5: 1142135
A6: 45689 | B6: Feb-2025 | C6: 2025 | D6: North | E6: 865476
A7: 45689 | B7: Feb-2025 | C7: 2025 | D7: South | E7: 923595
A8: 45689 | B8: Feb-2025 | C8: 2025 | D8: East | E8: 924049
A9: 45689 | B9: Feb-2025 | C9: 2025 | D9: West | E9: 854129
A10: 45717 | B10: Mar-2025 | C10: 2025 | D10: North | E10: 1239791
A11: 45717 | B11: Mar-2025 | C11: 2025 | D11: South | E11: 1012900
A12: 45717 | B12: Mar-2025 | C12: 2025 | D12: East | E12: 1093675
A13: 45717 | B13: Mar-2025 | C13: 2025 | D13: West | E13: 860174
... A81: 46235 | B81: Aug-2026 | C81: 2026 | D81: West | E81: 1085561

Sheet 06_Analysis
A1: MONTHLY SALES ANALYSIS
A3: Month | B3: Sales | C3: Profit | D3: Orders | E3: Target | F3: Achievement
A4: 45658 | B4: =SUMIFS('02_Sales_Data'!$L:$L,'02_Sales_Data'!$B:$B,">="&A4,'02_Sales_Data'!$B:$B,"<"&EDATE(A4,1)) | C4: =SUMIFS('02_Sales_Data'!$N:$N,'02_Sales_Data'!$B:$B,">="&A4,'02_Sales_Data'!$B:$B,"<"&EDATE(A4,1)) | D4: =COUNTIFS('02_Sales_Data'!$B:$B,">="&A4,'02_Sales_Data'!$B:$B,"<"&EDATE(A4,1)) | E4: =SUMIFS('05_Targets'!$E:$E,'05_Targets'!$A:$A,A4) | F4: =IFERROR(B4/E4,0)
A5: 45689 | B5: =SUMIFS('02_Sales_Data'!$L:$L,'02_Sales_Data'!$B:$B,">="&A5,'02_Sales_Data'!$B:$B,"<"&EDATE(A5,1)) | C5: =SUMIFS('02_Sales_Data'!$N:$N,'02_Sales_Data'!$B:$B,">="&A5,'02_Sales_Data'!$B:$B,"<"&EDATE(A5,1)) | D5: =COUNTIFS('02_Sales_Data'!$B:$B,">="&A5,'02_Sales_Data'!$B:$B,"<"&EDATE(A5,1)) | E5: =SUMIFS('05_Targets'!$E:$E,'05_Targets'!$A:$A,A5) | F5: =IFERROR(B5/E5,0)
A6: 45717 | B6: =SUMIFS('02_Sales_Data'!$L:$L,'02_Sales_Data'!$B:$B,">="&A6,'02_Sales_Data'!$B:$B,"<"&EDATE(A6,1)) | C6: =SUMIFS('02_Sales_Data'!$N:$N,'02_Sales_Data'!$B:$B,">="&A6,'02_Sales_Data'!$B:$B,"<"&EDATE(A6,1)) | D6: =COUNTIFS('02_Sales_Data'!$B:$B,">="&A6,'02_Sales_Data'!$B:$B,"<"&EDATE(A6,1)) | E6: =SUMIFS('05_Targets'!$E:$E,'05_Targets'!$A:$A,A6) | F6: =IFERROR(B6/E6,0)
A7: 45748 | B7: =SUMIFS('02_Sales_Data'!$L:$L,'02_Sales_Data'!$B:$B,">="&A7,'02_Sales_Data'!$B:$B,"<"&EDATE(A7,1)) | C7: =SUMIFS('02_Sales_Data'!$N:$N,'02_Sales_Data'!$B:$B,">="&A7,'02_Sales_Data'!$B:$B,"<"&EDATE(A7,1)) | D7: =COUNTIFS('02_Sales_Data'!$B:$B,">="&A7,'02_Sales_Data'!$B:$B,"<"&EDATE(A7,1)) | E7: =SUMIFS('05_Targets'!$E:$E,'05_Targets'!$A:$A,A7) | F7: =IFERROR(B7/E7,0)
A8: 45778 | B8: =SUMIFS('02_Sales_Data'!$L:$L,'02_Sales_Data'!$B:$B,">="&A8,'02_Sales_Data'!$B:$B,"<"&EDATE(A8,1)) | C8: =SUMIFS('02_Sales_Data'!$N:$N,'02_Sales_Data'!$B:$B,">="&A8,'02_Sales_Data'!$B:$B,"<"&EDATE(A8,1)) | D8: =COUNTIFS('02_Sales_Data'!$B:$B,">="&A8,'02_Sales_Data'!$B:$B,"<"&EDATE(A8,1)) | E8: =SUMIFS('05_Targets'!$E:$E,'05_Targets'!$A:$A,A8) | F8: =IFERROR(B8/E8,0)
A9: 45809 | B9: =SUMIFS('02_Sales_Data'!$L:$L,'02_Sales_Data'!$B:$B,">="&A9,'02_Sales_Data'!$B:$B,"<"&EDATE(A9,1)) | C9: =SUMIFS('02_Sales_Data'!$N:$N,'02_Sales_Data'!$B:$B,">="&A9,'02_Sales_Data'!$B:$B,"<"&EDATE(A9,1)) | D9: =COUNTIFS('02_Sales_Data'!$B:$B,">="&A9,'02_Sales_Data'!$B:$B,"<"&EDATE(A9,1)) | E9: =SUMIFS('05_Targets'!$E:$E,'05_Targets'!$A:$A,A9) | F9: =IFERROR(B9/E9,0)
A10: 45839 | B10: =SUMIFS('02_Sales_Data'!$L:$L,'02_Sales_Data'!$B:$B,">="&A10,'02_Sales_Data'!$B:$B,"<"&EDATE(A10,1)) | C10: =SUMIFS('02_Sales_Data'!$N:$N,'02_Sales_Data'!$B:$B,">="&A10,'02_Sales_Data'!$B:$B,"<"&EDATE(A10,1)) | D10: =COUNTIFS('02_Sales_Data'!$B:$B,">="&A10,'02_Sales_Data'!$B:$B,"<"&EDATE(A10,1)) | E10: =SUMIFS('05_Targets'!$E:$E,'05_Targets'!$A:$A,A10) | F10: =IFERROR(B10/E10,0)
A11: 45870 | B11: =SUMIFS('02_Sales_Data'!$L:$L,'02_Sales_Data'!$B:$B,">="&A11,'02_Sales_Data'!$B:$B,"<"&EDATE(A11,1)) | C11: =SUMIFS('02_Sales_Data'!$N:$N,'02_Sales_Data'!$B:$B,">="&A11,'02_Sales_Data'!$B:$B,"<"&EDATE(A11,1)) | D11: =COUNTIFS('02_Sales_Data'!$B:$B,">="&A11,'02_Sales_Data'!$B:$B,"<"&EDATE(A11,1)) | E11: =SUMIFS('05_Targets'!$E:$E,'05_Targets'!$A:$A,A11) | F11: =IFERROR(B11/E11,0)
A12: 45901 | B12: =SUMIFS('02_Sales_Data'!$L:$L,'02_Sales_Data'!$B:$B,">="&A12,'02_Sales_Data'!$B:$B,"<"&EDATE(A12,1)) | C12: =SUMIFS('02_Sales_Data'!$N:$N,'02_Sales_Data'!$B:$B,">="&A12,'02_Sales_Data'!$B:$B,"<"&EDATE(A12,1)) | D12: =COUNTIFS('02_Sales_Data'!$B:$B,">="&A12,'02_Sales_Data'!$B:$B,"<"&EDATE(A12,1)) | E12: =SUMIFS('05_Targets'!$E:$E,'05_Targets'!$A:$A,A12) | F12: =IFERROR(B12/E12,0)
A13: 45931 | B13: =SUMIFS('02_Sales_Data'!$L:$L,'02_Sales_Data'!$B:$B,">="&A13,'02_Sales_Data'!$B:$B,"<"&EDATE(A13,1)) | C13: =SUMIFS('02_Sales_Data'!$N:$N,'02_Sales_Data'!$B:$B,">="&A13,'02_Sales_Data'!$B:$B,"<"&EDATE(A13,1)) | D13: =COUNTIFS('02_Sales_Data'!$B:$B,">="&A13,'02_Sales_Data'!$B:$B,"<"&EDATE(A13,1)) | E13: =SUMIFS('05_Targets'!$E:$E,'05_Targets'!$A:$A,A13) | F13: =IFERROR(B13/E13,0)
A14: 45962 | B14: =SUMIFS('02_Sales_Data'!$L:$L,'02_Sales_Data'!$B:$B,">="&A14,'02_Sales_Data'!$B:$B,"<"&EDATE(A14,1)) | C14: =SUMIFS('02_Sales_Data'!$N:$N,'02_Sales_Data'!$B:$B,">="&A14,'02_Sales_Data'!$B:$B,"<"&EDATE(A14,1)) | D14: =COUNTIFS('02_Sales_Data'!$B:$B,">="&A14,'02_Sales_Data'!$B:$B,"<"&EDATE(A14,1)) | E14: =SUMIFS('05_Targets'!$E:$E,'05_Targets'!$A:$A,A14) | F14: =IFERROR(B14/E14,0)
A15: 45992 | B15: =SUMIFS('02_Sales_Data'!$L:$L,'02_Sales_Data'!$B:$B,">="&A15,'02_Sales_Data'!$B:$B,"<"&EDATE(A15,1)) | C15: =SUMIFS('02_Sales_Data'!$N:$N,'02_Sales_Data'!$B:$B,">="&A15,'02_Sales_Data'!$B:$B,"<"&EDATE(A15,1)) | D15: =COUNTIFS('02_Sales_Data'!$B:$B,">="&A15,'02_Sales_Data'!$B:$B,"<"&EDATE(A15,1)) | E15: =SUMIFS('05_Targets'!$E:$E,'05_Targets'!$A:$A,A15) | F15: =IFERROR(B15/E15,0)
... A23: 46235 | B23: =SUMIFS('02_Sales_Data'!$L:$L,'02_Sales_Data'!$B:$B,">="&A23,'02_Sales_Data'!$B:$B,"<"&EDATE(A23,1)) | C23: =SUMIFS('02_Sales_Data'!$N:$N,'02_Sales_Data'!$B:$B,">="&A23,'02_Sales_Data'!$B:$B,"<"&EDATE(A23,1)) | D23: =COUNTIFS('02_Sales_Data'!$B:$B,">="&A23,'02_Sales_Data'!$B:$B,"<"&EDATE(A23,1)) | E23: =SUMIFS('05_Targets'!$E:$E,'05_Targets'!$A:$A,A23) | F23: =IFERROR(B23/E23,0)
A25: REGIONAL ANALYSIS
A27: Region | B27: Sales | C27: Profit | D27: Orders | E27: Margin
A28: North | B28: =SUMIFS('02_Sales_Data'!$L:$L,'02_Sales_Data'!$C:$C,A28) | C28: =SUMIFS('02_Sales_Data'!$N:$N,'02_Sales_Data'!$C:$C,A28) | D28: =COUNTIF('02_Sales_Data'!$C:$C,A28) | E28: =IFERROR(C28/B28,0)
A29: South | B29: =SUMIFS('02_Sales_Data'!$L:$L,'02_Sales_Data'!$C:$C,A29) | C29: =SUMIFS('02_Sales_Data'!$N:$N,'02_Sales_Data'!$C:$C,A29) | D29: =COUNTIF('02_Sales_Data'!$C:$C,A29) | E29: =IFERROR(C29/B29,0)
A30: East | B30: =SUMIFS('02_Sales_Data'!$L:$L,'02_Sales_Data'!$C:$C,A30) | C30: =SUMIFS('02_Sales_Data'!$N:$N,'02_Sales_Data'!$C:$C,A30) | D30: =COUNTIF('02_Sales_Data'!$C:$C,A30) | E30: =IFERROR(C30/B30,0)
A31: West | B31: =SUMIFS('02_Sales_Data'!$L:$L,'02_Sales_Data'!$C:$C,A31) | C31: =SUMIFS('02_Sales_Data'!$N:$N,'02_Sales_Data'!$C:$C,A31) | D31: =COUNTIF('02_Sales_Data'!$C:$C,A31) | E31: =IFERROR(C31/B31,0)
A32: CATEGORY ANALYSIS
A34: Category | B34: Sales | C34: Profit | D34: Orders | E34: Margin
A35: Accessories | B35: =SUMIFS('02_Sales_Data'!$L:$L,'02_Sales_Data'!$G:$G,A35) | C35: =SUMIFS('02_Sales_Data'!$N:$N,'02_Sales_Data'!$G:$G,A35) | D35: =COUNTIF('02_Sales_Data'!$G:$G,A35) | E35: =IFERROR(C35/B35,0)
A36: Electronics | B36: =SUMIFS('02_Sales_Data'!$L:$L,'02_Sales_Data'!$G:$G,A36) | C36: =SUMIFS('02_Sales_Data'!$N:$N,'02_Sales_Data'!$G:$G,A36) | D36: =COUNTIF('02_Sales_Data'!$G:$G,A36) | E36: =IFERROR(C36/B36,0)
A37: Furniture | B37: =SUMIFS('02_Sales_Data'!$L:$L,'02_Sales_Data'!$G:$G,A37) | C37: =SUMIFS('02_Sales_Data'!$N:$N,'02_Sales_Data'!$G:$G,A37) | D37: =COUNTIF('02_Sales_Data'!$G:$G,A37) | E37: =IFERROR(C37/B37,0)
A38: Networking | B38: =SUMIFS('02_Sales_Data'!$L:$L,'02_Sales_Data'!$G:$G,A38) | C38: =SUMIFS('02_Sales_Data'!$N:$N,'02_Sales_Data'!$G:$G,A38) | D38: =COUNTIF('02_Sales_Data'!$G:$G,A38) | E38: =IFERROR(C38/B38,0)
A39: Office Supplies | B39: =SUMIFS('02_Sales_Data'!$L:$L,'02_Sales_Data'!$G:$G,A39) | C39: =SUMIFS('02_Sales_Data'!$N:$N,'02_Sales_Data'!$G:$G,A39) | D39: =COUNTIF('02_Sales_Data'!$G:$G,A39) | E39: =IFERROR(C39/B39,0)
A42: SALESPERSON ANALYSIS
A44: Salesperson | B44: Sales | C44: Profit | D44: Orders | E44: Margin
A45: Amit | B45: =SUMIFS('02_Sales_Data'!$L:$L,'02_Sales_Data'!$E:$E,A45) | C45: =SUMIFS('02_Sales_Data'!$N:$N,'02_Sales_Data'!$E:$E,A45) | D45: =COUNTIF('02_Sales_Data'!$E:$E,A45) | E45: =IFERROR(C45/B45,0)
A46: Priya | B46: =SUMIFS('02_Sales_Data'!$L:$L,'02_Sales_Data'!$E:$E,A46) | C46: =SUMIFS('02_Sales_Data'!$N:$N,'02_Sales_Data'!$E:$E,A46) | D46: =COUNTIF('02_Sales_Data'!$E:$E,A46) | E46: =IFERROR(C46/B46,0)
A47: Rahul | B47: =SUMIFS('02_Sales_Data'!$L:$L,'02_Sales_Data'!$E:$E,A47) | C47: =SUMIFS('02_Sales_Data'!$N:$N,'02_Sales_Data'!$E:$E,A47) | D47: =COUNTIF('02_Sales_Data'!$E:$E,A47) | E47: =IFERROR(C47/B47,0)
A48: Sneha | B48: =SUMIFS('02_Sales_Data'!$L:$L,'02_Sales_Data'!$E:$E,A48) | C48: =SUMIFS('02_Sales_Data'!$N:$N,'02_Sales_Data'!$E:$E,A48) | D48: =COUNTIF('02_Sales_Data'!$E:$E,A48) | E48: =IFERROR(C48/B48,0)
A49: Vikram | B49: =SUMIFS('02_Sales_Data'!$L:$L,'02_Sales_Data'!$E:$E,A49) | C49: =SUMIFS('02_Sales_Data'!$N:$N,'02_Sales_Data'!$E:$E,A49) | D49: =COUNTIF('02_Sales_Data'!$E:$E,A49) | E49: =IFERROR(C49/B49,0)
A50: Neha | B50: =SUMIFS('02_Sales_Data'!$L:$L,'02_Sales_Data'!$E:$E,A50) | C50: =SUMIFS('02_Sales_Data'!$N:$N,'02_Sales_Data'!$E:$E,A50) | D50: =COUNTIF('02_Sales_Data'!$E:$E,A50) | E50: =IFERROR(C50/B50,0)
A51: Arjun | B51: =SUMIFS('02_Sales_Data'!$L:$L,'02_Sales_Data'!$E:$E,A51) | C51: =SUMIFS('02_Sales_Data'!$N:$N,'02_Sales_Data'!$E:$E,A51) | D51: =COUNTIF('02_Sales_Data'!$E:$E,A51) | E51: =IFERROR(C51/B51,0)
A52: Kavya | B52: =SUMIFS('02_Sales_Data'!$L:$L,'02_Sales_Data'!$E:$E,A52) | C52: =SUMIFS('02_Sales_Data'!$N:$N,'02_Sales_Data'!$E:$E,A52) | D52: =COUNTIF('02_Sales_Data'!$E:$E,A52) | E52: =IFERROR(C52/B52,0)

Sheet 07_Dashboard
A1: SALES PERFORMANCE DASHBOARD
A4: Dashboard Filter | B4: All | C4: Region | D4: All | E4: Category | F4: All
A6: Total Sales | C6: Total Profit | E6: Profit Margin | G6: Orders | I6: Units Sold | K6: Target Achievement
A7: ='04_Calculations'!B2 | C7: ='04_Calculations'!B3 | E7: ='04_Calculations'!B4 | G7: ='04_Calculations'!B5 | I7: ='04_Calculations'!B6 | K7: ='04_Calculations'!B9
A20: Month | B20: Sales | C20: Target | E20: Region | F20: Sales | H20: Category | I20: Sales | K20: Salesperson | L20: Sales
A21: ='06_Analysis'!A4 | B21: ='06_Analysis'!B4 | C21: ='06_Analysis'!E4 | E21: ='06_Analysis'!A28 | F21: ='06_Analysis'!B28 | H21: ='06_Analysis'!A35 | I21: ='06_Analysis'!B35 | K21: ='06_Analysis'!A45 | L21: ='06_Analysis'!B45
A22: ='06_Analysis'!A5 | B22: ='06_Analysis'!B5 | C22: ='06_Analysis'!E5 | E22: ='06_Analysis'!A29 | F22: ='06_Analysis'!B29 | H22: ='06_Analysis'!A36 | I22: ='06_Analysis'!B36 | K22: ='06_Analysis'!A46 | L22: ='06_Analysis'!B46
A23: ='06_Analysis'!A6 | B23: ='06_Analysis'!B6 | C23: ='06_Analysis'!E6 | E23: ='06_Analysis'!A30 | F23: ='06_Analysis'!B30 | H23: ='06_Analysis'!A37 | I23: ='06_Analysis'!B37 | K23: ='06_Analysis'!A47 | L23: ='06_Analysis'!B47
A24: ='06_Analysis'!A7 | B24: ='06_Analysis'!B7 | C24: ='06_Analysis'!E7 | E24: ='06_Analysis'!A31 | F24: ='06_Analysis'!B31 | H24: ='06_Analysis'!A38 | I24: ='06_Analysis'!B38 | K24: ='06_Analysis'!A48 | L24: ='06_Analysis'!B48
A25: ='06_Analysis'!A8 | B25: ='06_Analysis'!B8 | C25: ='06_Analysis'!E8 | H25: ='06_Analysis'!A39 | I25: ='06_Analysis'!B39 | K25: ='06_Analysis'!A49 | L25: ='06_Analysis'!B49
A26: ='06_Analysis'!A9 | B26: ='06_Analysis'!B9 | C26: ='06_Analysis'!E9 | K26: ='06_Analysis'!A50 | L26: ='06_Analysis'!B50
A27: ='06_Analysis'!A10 | B27: ='06_Analysis'!B10 | C27: ='06_Analysis'!E10 | K27: ='06_Analysis'!A51 | L27: ='06_Analysis'!B51
A28: ='06_Analysis'!A11 | B28: ='06_Analysis'!B11 | C28: ='06_Analysis'!E11 | K28: ='06_Analysis'!A52 | L28: ='06_Analysis'!B52
A29: ='06_Analysis'!A12 | B29: ='06_Analysis'!B12 | C29: ='06_Analysis'!E12
A30: ='06_Analysis'!A13 | B30: ='06_Analysis'!B13 | C30: ='06_Analysis'!E13
A31: ='06_Analysis'!A14 | B31: ='06_Analysis'!B14 | C31: ='06_Analysis'!E14
A32: ='06_Analysis'!A15 | B32: ='06_Analysis'!B15 | C32: ='06_Analysis'!E15
A33: ='06_Analysis'!A16 | B33: ='06_Analysis'!B16 | C33: ='06_Analysis'!E16
A34: ='06_Analysis'!A17 | B34: ='06_Analysis'!B17 | C34: ='06_Analysis'!E17
A35: ='06_Analysis'!A18 | B35: ='06_Analysis'!B18 | C35: ='06_Analysis'!E18
A36: ='06_Analysis'!A19 | B36: ='06_Analysis'!B19 | C36: ='06_Analysis'!E19
A37: ='06_Analysis'!A20 | B37: ='06_Analysis'!B20 | C37: ='06_Analysis'!E20
A38: ='06_Analysis'!A21 | B38: ='06_Analysis'!B21 | C38: ='06_Analysis'!E21
A39: ='06_Analysis'!A22 | B39: ='06_Analysis'!B22 | C39: ='06_Analysis'!E22
A40: ='06_Analysis'!A23 | B40: ='06_Analysis'!B23 | C40: ='06_Analysis'!E23

Sheet 08_Insights
A1: BUSINESS INSIGHTS & RECOMMENDATIONS
A4: 1. Revenue Trend | B4: Use the monthly sales chart to identify periods of growth, seasonality and target gaps.
A5: 2. Regional Performance | B5: Compare regional sales and margin to identify high-contribution markets and areas below plan.
A6: 3. Product Mix | B6: Use category performance to identify categories that combine strong revenue with healthy margins.
A7: 4. Salesperson Productivity | B7: Compare sales, order volume and margin to understand individual contribution.
A8: 5. Target Management | B8: Track Target Achievement and investigate months/regions where actual sales fall below target.
A9: 6. Discount Impact | B9: Review high-discount transactions alongside profit margin to identify potential margin leakage.
A10: 7. Revenue Concentration | B10: Monitor the contribution of leading products/customers to understand concentration risk.
